pasqal_cloud/__init__.py
pasqal_cloud/_version.py
pasqal_cloud/authentication.py
pasqal_cloud/batch.py
pasqal_cloud/client.py
pasqal_cloud/endpoints.py
pasqal_cloud/errors.py
pasqal_cloud/job.py
pasqal_cloud/project.py
pasqal_cloud/py.typed
pasqal_cloud/workload.py
pasqal_cloud/device/__init__.py
pasqal_cloud/device/device_types.py
pasqal_cloud/device/emulator_types.py
pasqal_cloud/device/configuration/__init__.py
pasqal_cloud/device/configuration/base_config.py
pasqal_cloud/device/configuration/emu_free.py
pasqal_cloud/device/configuration/emu_fresnel.py
pasqal_cloud/device/configuration/emu_tn.py
pasqal_cloud/device/configuration/result_type.py
pasqal_cloud/utils/__init__.py
pasqal_cloud/utils/constants.py
pasqal_cloud/utils/filters.py
pasqal_cloud/utils/jsend.py
pasqal_cloud/utils/mock_server.py
pasqal_cloud/utils/responses.py
pasqal_cloud/utils/retry.py
pasqal_cloud/utils/strenum.py
pasqal_cloud-0.20.8.dist-info/licenses/LICENSE
pasqal_cloud-0.20.8.dist-info/METADATA
pasqal_cloud-0.20.8.dist-info/WHEEL
pasqal_cloud-0.20.8.dist-info/top_level.txt
pasqal_cloud-0.20.8.dist-info/RECORD
