Metadata-Version: 2.4
Name: pasqal-cloud
Version: 0.20.8
Summary: Software development kit for Pasqal cloud platform.
Home-page: https://github.com/pasqal-io/pasqal-cloud
Maintainer: Pasqal Cloud Services
Maintainer-email: pcs@pasqal.io
License: Apache 2.0
Classifier: Development Status :: 3 - Alpha
Classifier: Programming Language :: Python :: 3
Requires-Python: >=3.9
License-File: LICENSE
Requires-Dist: auth0-python<4.0.0,>=3.23.1
Requires-Dist: requests<3.0.0,>=2.25.1
Requires-Dist: pyjwt[crypto]<3.0.0,>=2.5.0
Requires-Dist: pydantic<3.0.0,>=2.6.0
Requires-Dist: requests-mock==1.12.1
Provides-Extra: dev
Requires-Dist: ruff==0.6.9; extra == "dev"
Requires-Dist: pytest==8.1.1; extra == "dev"
Requires-Dist: mypy==1.10.0; extra == "dev"
Requires-Dist: types-requests==2.31.0.1; extra == "dev"
Requires-Dist: pytest-cov==5.0.0; extra == "dev"
Provides-Extra: docs
Requires-Dist: mkdocstrings==0.27.0; extra == "docs"
Requires-Dist: mkdocstrings-python==1.13.0; extra == "docs"
Requires-Dist: mkdocs-material==9.5.50; extra == "docs"
Requires-Dist: mkdocs==1.6.1; extra == "docs"
Dynamic: classifier
Dynamic: description
Dynamic: description-content-type
Dynamic: home-page
Dynamic: license
Dynamic: license-file
Dynamic: maintainer
Dynamic: maintainer-email
Dynamic: provides-extra
Dynamic: requires-dist
Dynamic: requires-python
Dynamic: summary
